<annotation>
	<folder>penguins_dataset</folder>
	<filename>4869355660_d33116a529_o.jpg</filename>
	<path>C:\Users\srolz1\Desktop\Coding Bootcamp\Project3\SwaddlesForWaddles\imageAI\penguins_dataset\4869355660_d33116a529_o.jpg</path>
	<source>
		<database>Unknown</database>
	</source>
	<size>
		<width>2848</width>
		<height>2136</height>
		<depth>3</depth>
	</size>
	<segmented>0</segmented>
	<object>
		<name>penguin</name>
		<pose>Unspecified</pose>
		<truncated>0</truncated>
		<difficult>0</difficult>
		<bndbox>
			<xmin>825</xmin>
			<ymin>293</ymin>
			<xmax>1902</xmax>
			<ymax>1735</ymax>
		</bndbox>
	</object>
	<object>
		<name>penguin</name>
		<pose>Unspecified</pose>
		<truncated>1</truncated>
		<difficult>0</difficult>
		<bndbox>
			<xmin>2257</xmin>
			<ymin>493</ymin>
			<xmax>2848</xmax>
			<ymax>1676</ymax>
		</bndbox>
	</object>
</annotation>
